odoo/addons/account_group_menu/README.rst
odoo/addons/account_group_menu/__init__.py
odoo/addons/account_group_menu/__manifest__.py
odoo/addons/account_group_menu/demo/account_group.xml
odoo/addons/account_group_menu/demo/account_tax_group.xml
odoo/addons/account_group_menu/i18n/account_group_menu.pot
odoo/addons/account_group_menu/i18n/ar.po
odoo/addons/account_group_menu/i18n/da.po
odoo/addons/account_group_menu/i18n/de.po
odoo/addons/account_group_menu/i18n/es.po
odoo/addons/account_group_menu/i18n/fr.po
odoo/addons/account_group_menu/i18n/hr.po
odoo/addons/account_group_menu/i18n/it.po
odoo/addons/account_group_menu/i18n/pt.po
odoo/addons/account_group_menu/models/__init__.py
odoo/addons/account_group_menu/models/account_group.py
odoo/addons/account_group_menu/models/account_tax_group.py
odoo/addons/account_group_menu/readme/CONTRIBUTORS.rst
odoo/addons/account_group_menu/readme/DESCRIPTION.rst
odoo/addons/account_group_menu/static/description/icon.png
odoo/addons/account_group_menu/static/description/index.html
odoo/addons/account_group_menu/views/account_group.xml
odoo/addons/account_group_menu/views/account_tax_group.xml
odoo12_addon_account_group_menu-12.0.1.0.0.99.dev22.dist-info/METADATA
odoo12_addon_account_group_menu-12.0.1.0.0.99.dev22.dist-info/WHEEL
odoo12_addon_account_group_menu-12.0.1.0.0.99.dev22.dist-info/top_level.txt
odoo12_addon_account_group_menu-12.0.1.0.0.99.dev22.dist-info/RECORD
